{
  "id": "ch03_02b_serious",
  "commands": [
    {
      "type": "FLAG_SET",
      "key": "flag_h1_first_tone",
      "value": "serious"
    },
    {
      "type": "DIALOGUE",
      "speaker": "구윤모",
      "text": "공부 열심히 할게요."
    },
    {
      "type": "CHARACTER",
      "id": "차세린",
      "sprite": "smile",
      "position": "right",
      "transition": "fade"
    },
    {
      "type": "DIALOGUE",
      "speaker": "차세린",
      "text": "갑자기 진중하시네요."
    },
    {
      "type": "DIALOGUE",
      "speaker": "구윤모",
      "text": "의국까지 잘못 들어와서 길 알려주시는데, 인사가 가벼우면 좀 그래서요."
    },
    {
      "type": "DIALOGUE",
      "speaker": "차세린",
      "text": "그래요. 본과 1학년이 그렇게 진중하게 인사하는 거 흔치 않은데. 6년, 같이 갑시다."
    },
    {
      "type": "DIALOGUE",
      "speaker": "구윤모",
      "text": "네. 잘 부탁드리겠습니다."
    },
    {
      "type": "JUMP",
      "sceneId": "ch03_03_card_exchange"
    }
  ],
  "meta": {
    "chapter": 3,
    "time": "2026-04-06 morning, dongsan hospital",
    "activeHeroines": [
      "H1"
    ]
  }
}